{"time":1573073053901,"information":"world-aligned-accel","value":"[0.31277066, 0.95173, 19.890572]","dataType":"DATA"}
{"time":1573073053961,"information":"world-aligned-accel","value":"[0.29380792, 0.96542096, 19.879065]","dataType":"DATA"}
{"time":1573073054030,"information":"world-aligned-accel","value":"[0.31133285, 0.95319486, 19.880196]","dataType":"DATA"}
{"time":1573073054090,"information":"world-aligned-accel","value":"[0.29939044, 0.9592718, 19.898174]","dataType":"DATA"}
{"time":1573073054151,"information":"world-aligned-accel","value":"[0.31071472, 0.96243834, 19.900808]","dataType":"DATA"}
{"time":1573073054211,"information":"world-aligned-accel","value":"[0.29257894, 0.9654952, 19.879787]","dataType":"DATA"}
{"time":1573073054283,"information":"world-aligned-accel","value":"[0.29499006, 0.9614229, 19.896065]","dataType":"DATA"}
{"time":1573073054334,"information":"world-aligned-accel","value":"[0.30325463, 0.9548199, 19.87592]","dataType":"DATA"}
{"time":1573073054398,"information":"world-aligned-accel","value":"[0.30466402, 0.95743513, 19.895023]","dataType":"DATA"}
{"time":1573073054458,"information":"world-aligned-accel","value":"[0.31630015, 0.9583326, 19.879314]","dataType":"DATA"}
{"time":1573073054523,"information":"world-aligned-accel","value":"[0.31596535, 0.9689968, 19.886568]","dataType":"DATA"}
{"time":1573073054588,"information":"world-aligned-accel","value":"[0.30492413, 0.96211755, 19.86985]","dataType":"DATA"}
{"time":1573073054649,"information":"world-aligned-accel","value":"[0.2857632, 0.9705297, 19.911179]","dataType":"DATA"}
{"time":1573073054710,"information":"world-aligned-accel","value":"[0.30242836, 0.94502044, 19.877548]","dataType":"DATA"}
{"time":1573073054772,"information":"world-aligned-accel","value":"[0.303743, 0.95965505, 19.883282]","dataType":"DATA"}
{"time":1573073054841,"information":"world-aligned-accel","value":"[0.2995855, 0.96191525, 19.885708]","dataType":"DATA"}
{"time":1573073054897,"information":"world-aligned-accel","value":"[0.2983896, 0.96077085, 19.881851]","dataType":"DATA"}
{"time":1573073054957,"information":"world-aligned-accel","value":"[0.3100294, 0.96134776, 19.892689]","dataType":"DATA"}
{"time":1573073055022,"information":"world-aligned-accel","value":"[0.29963732, 0.95224833, 19.902025]","dataType":"DATA"}
{"time":1573073055085,"information":"world-aligned-accel","value":"[0.29453403, 0.95647943, 19.895393]","dataType":"DATA"}
{"time":1573073055147,"information":"world-aligned-accel","value":"[0.3059572, 0.9675287, 19.890593]","dataType":"DATA"}
{"time":1573073055205,"information":"world-aligned-accel","value":"[0.30869287, 0.9569348, 19.889097]","dataType":"DATA"}
{"time":1573073055271,"information":"world-aligned-accel","value":"[0.3073907, 0.9626118, 19.880875]","dataType":"DATA"}
{"time":1573073055330,"information":"world-aligned-accel","value":"[0.2947299, 0.95897734, 19.89386]","dataType":"DATA"}
{"time":1573073055396,"information":"world-aligned-accel","value":"[0.29851028, 0.94629496, 19.894663]","dataType":"DATA"}
{"time":1573073055454,"information":"world-aligned-accel","value":"[0.313344, 0.9619565, 19.87323]","dataType":"DATA"}
{"time":1573073055521,"information":"world-aligned-accel","value":"[0.31276792, 0.95562494, 19.894917]","dataType":"DATA"}
{"time":1573073055579,"information":"world-aligned-accel","value":"[0.31499448, 0.95659244, 19.88887]","dataType":"DATA"}
{"time":1573073055646,"information":"world-aligned-accel","value":"[0.30055156, 0.96169615, 19.865376]","dataType":"DATA"}
{"time":1573073055707,"information":"world-aligned-accel","value":"[0.30952024, 0.95962065, 19.890392]","dataType":"DATA"}
{"time":1573073055777,"information":"world-aligned-accel","value":"[0.30371958, 0.96873605, 19.89635]","dataType":"DATA"}
{"time":1573073055827,"information":"world-aligned-accel","value":"[0.30518833, 0.9610133, 19.892696]","dataType":"DATA"}
{"time":1573073055890,"information":"world-aligned-accel","value":"[0.30159226, 0.95192957, 19.896576]","dataType":"DATA"}
{"time":1573073055954,"information":"world-aligned-accel","value":"[0.30915856, 0.9619996, 19.887268]","dataType":"DATA"}
{"time":1573073056016,"information":"world-aligned-accel","value":"[0.29626068, 0.97676444, 19.89924]","dataType":"DATA"}
{"time":1573073056076,"information":"world-aligned-accel","value":"[0.28979647, 0.9914801, 19.897755]","dataType":"DATA"}
{"time":1573073056141,"information":"world-aligned-accel","value":"[0.30029064, 0.99498266, 19.897388]","dataType":"DATA"}
{"time":1573073056202,"information":"world-aligned-accel","value":"[0.29524028, 0.97350025, 19.887474]","dataType":"DATA"}
{"time":1573073056265,"information":"world-aligned-accel","value":"[0.30138677, 0.97686076, 19.892458]","dataType":"DATA"}
{"time":1573073056325,"information":"world-aligned-accel","value":"[0.2920197, 0.98566484, 19.887344]","dataType":"DATA"}
{"time":1573073056390,"information":"world-aligned-accel","value":"[0.29681063, 0.99154973, 19.878197]","dataType":"DATA"}
{"time":1573073056449,"information":"world-aligned-accel","value":"[0.30881232, 0.9729657, 19.887]","dataType":"DATA"}
{"time":1573073056515,"information":"world-aligned-accel","value":"[0.30632898, 0.98192394, 19.901915]","dataType":"DATA"}
{"time":1573073056577,"information":"world-aligned-accel","value":"[0.30378097, 0.9822948, 19.892357]","dataType":"DATA"}
{"time":1573073056638,"information":"world-aligned-accel","value":"[0.30670488, 0.97698975, 19.900402]","dataType":"DATA"}
{"time":1573073056698,"information":"world-aligned-accel","value":"[0.30147904, 0.968315, 19.899977]","dataType":"DATA"}
{"time":1573073056763,"information":"world-aligned-accel","value":"[0.3065709, 0.96157575, 19.873203]","dataType":"DATA"}
{"time":1573073056822,"information":"world-aligned-accel","value":"[0.29706722, 0.95813715, 19.895088]","dataType":"DATA"}
{"time":1573073056889,"information":"world-aligned-accel","value":"[0.2987162, 0.9526026, 19.875828]","dataType":"DATA"}
{"time":1573073056948,"information":"world-aligned-accel","value":"[0.30549455, 0.9719213, 19.885109]","dataType":"DATA"}
{"time":1573073057014,"information":"world-aligned-accel","value":"[0.298308, 0.96042246, 19.897324]","dataType":"DATA"}
{"time":1573073057074,"information":"world-aligned-accel","value":"[0.29500204, 0.9673793, 19.894365]","dataType":"DATA"}
{"time":1573073057139,"information":"world-aligned-accel","value":"[0.29804596, 0.97293687, 19.890528]","dataType":"DATA"}
{"time":1573073057195,"information":"world-aligned-accel","value":"[0.31017202, 0.9566224, 19.891153]","dataType":"DATA"}
{"time":1573073057269,"information":"world-aligned-accel","value":"[0.30808544, 0.9561273, 19.885906]","dataType":"DATA"}
{"time":1573073057321,"information":"world-aligned-accel","value":"[0.30515754, 0.97174144, 19.886627]","dataType":"DATA"}
{"time":1573073057383,"information":"world-aligned-accel","value":"[0.3016512, 0.94954675, 19.893654]","dataType":"DATA"}
{"time":1573073057447,"information":"world-aligned-accel","value":"[0.30837816, 0.95696044, 19.894152]","dataType":"DATA"}
{"time":1573073057508,"information":"world-aligned-accel","value":"[0.3080576, 0.9640368, 19.888832]","dataType":"DATA"}
{"time":1573073057568,"information":"world-aligned-accel","value":"[0.30948156, 0.9728738, 19.894623]","dataType":"DATA"}
{"time":1573073057634,"information":"world-aligned-accel","value":"[0.29883653, 0.96726215, 19.88985]","dataType":"DATA"}
{"time":1573073057696,"information":"world-aligned-accel","value":"[0.3024915, 0.97168106, 19.880102]","dataType":"DATA"}
{"time":1573073057756,"information":"world-aligned-accel","value":"[0.30004394, 0.9677386, 19.903275]","dataType":"DATA"}
{"time":1573073057820,"information":"world-aligned-accel","value":"[0.29768965, 0.9669157, 19.881783]","dataType":"DATA"}
{"time":1573073057882,"information":"world-aligned-accel","value":"[0.30572227, 0.97418797, 19.888214]","dataType":"DATA"}
{"time":1573073057948,"information":"world-aligned-accel","value":"[0.3062572, 0.9559016, 19.877275]","dataType":"DATA"}
{"time":1573073058026,"information":"world-aligned-accel","value":"[0.29773447, 0.96126103, 19.891563]","dataType":"DATA"}
{"time":1573073058072,"information":"world-aligned-accel","value":"[0.30158937, 0.969687, 19.882423]","dataType":"DATA"}
{"time":1573073058129,"information":"world-aligned-accel","value":"[0.3059196, 0.95932204, 19.890636]","dataType":"DATA"}
{"time":1573073058190,"information":"world-aligned-accel","value":"[0.29856235, 0.9740487, 19.866085]","dataType":"DATA"}
{"time":1573073058257,"information":"world-aligned-accel","value":"[0.3019083, 0.95342195, 19.899736]","dataType":"DATA"}
{"time":1573073058315,"information":"world-aligned-accel","value":"[0.29381686, 0.9768348, 19.892952]","dataType":"DATA"}
{"time":1573073058380,"information":"world-aligned-accel","value":"[0.32071847, 0.95338476, 19.891092]","dataType":"DATA"}
{"time":1573073058441,"information":"world-aligned-accel","value":"[0.30172366, 0.97920704, 19.885336]","dataType":"DATA"}
{"time":1573073058505,"information":"world-aligned-accel","value":"[0.3177318, 0.97870636, 19.898296]","dataType":"DATA"}
{"time":1573073058567,"information":"world-aligned-accel","value":"[0.29535788, 0.950837, 19.875523]","dataType":"DATA"}
{"time":1573073058632,"information":"world-aligned-accel","value":"[0.30509144, 0.9432265, 19.87016]","dataType":"DATA"}
{"time":1573073058690,"information":"world-aligned-accel","value":"[0.28903168, 0.9712124, 19.916313]","dataType":"DATA"}
{"time":1573073058759,"information":"world-aligned-accel","value":"[0.29483485, 0.94211257, 19.87553]","dataType":"DATA"}
{"time":1573073058811,"information":"world-aligned-accel","value":"[0.2941897, 0.96328545, 19.876913]","dataType":"DATA"}
{"time":1573073058876,"information":"world-aligned-accel","value":"[0.29280043, 0.952574, 19.886818]","dataType":"DATA"}
{"time":1573073058938,"information":"world-aligned-accel","value":"[0.29802006, 0.9576005, 19.868755]","dataType":"DATA"}
{"time":1573073059000,"information":"world-aligned-accel","value":"[0.3113337, 0.9447633, 19.845634]","dataType":"DATA"}
{"time":1573073059061,"information":"world-aligned-accel","value":"[0.3037924, 0.9640656, 19.927742]","dataType":"DATA"}
{"time":1573073059125,"information":"world-aligned-accel","value":"[0.29066813, 0.9768628, 19.901218]","dataType":"DATA"}
{"time":1573073059190,"information":"world-aligned-accel","value":"[0.31828505, 0.9696444, 19.878256]","dataType":"DATA"}
{"time":1573073059249,"information":"world-aligned-accel","value":"[0.29879808, 0.94729567, 19.886415]","dataType":"DATA"}
{"time":1573073059309,"information":"world-aligned-accel","value":"[0.30862603, 0.9775903, 19.879105]","dataType":"DATA"}
{"time":1573073059374,"information":"world-aligned-accel","value":"[0.29735768, 0.95998514, 19.884825]","dataType":"DATA"}
{"time":1573073059434,"information":"world-aligned-accel","value":"[0.3068071, 0.97402924, 19.890987]","dataType":"DATA"}
{"time":1573073059499,"information":"world-aligned-accel","value":"[0.30708545, 0.97173667, 19.87399]","dataType":"DATA"}
{"time":1573073059562,"information":"world-aligned-accel","value":"[0.30303952, 0.9797871, 19.882097]","dataType":"DATA"}
{"time":1573073059622,"information":"world-aligned-accel","value":"[0.3027566, 0.9793885, 19.852364]","dataType":"DATA"}
{"time":1573073059682,"information":"world-aligned-accel","value":"[0.28407878, 0.97347665, 19.892937]","dataType":"DATA"}
{"time":1573073059749,"information":"world-aligned-accel","value":"[0.30244124, 0.977602, 19.877522]","dataType":"DATA"}
{"time":1573073059806,"information":"world-aligned-accel","value":"[0.30526578, 0.9799669, 19.871567]","dataType":"DATA"}
{"time":1573073059872,"information":"world-aligned-accel","value":"[0.29115665, 1.0028442, 19.89238]","dataType":"DATA"}
{"time":1573073059933,"information":"world-aligned-accel","value":"[0.30789337, 0.9873692, 19.874283]","dataType":"DATA"}
{"time":1573073059997,"information":"world-aligned-accel","value":"[0.3080297, 0.97660804, 19.872887]","dataType":"DATA"}
{"time":1573073060055,"information":"world-aligned-accel","value":"[0.28631327, 0.9875251, 19.882315]","dataType":"DATA"}
{"time":1573073060125,"information":"world-aligned-accel","value":"[0.2994867, 0.9810835, 19.879078]","dataType":"DATA"}
{"time":1573073060180,"information":"world-aligned-accel","value":"[0.30368608, 0.9838325, 19.880423]","dataType":"DATA"}
{"time":1573073060249,"information":"world-aligned-accel","value":"[0.28630024, 0.98898894, 19.882944]","dataType":"DATA"}
{"time":1573073060307,"information":"world-aligned-accel","value":"[0.30959564, 0.9818639, 19.878714]","dataType":"DATA"}
{"time":1573073060368,"information":"world-aligned-accel","value":"[0.29514414, 0.97974193, 19.873901]","dataType":"DATA"}
{"time":1573073060431,"information":"world-aligned-accel","value":"[0.30242032, 0.9816345, 19.887114]","dataType":"DATA"}
{"time":1573073060492,"information":"world-aligned-accel","value":"[0.2920863, 0.9802617, 19.874735]","dataType":"DATA"}
{"time":1573073060553,"information":"world-aligned-accel","value":"[0.29923126, 0.9787703, 19.883518]","dataType":"DATA"}
{"time":1573073060617,"information":"world-aligned-accel","value":"[0.3030197, 0.98985934, 19.883999]","dataType":"DATA"}
{"time":1573073060677,"information":"world-aligned-accel","value":"[0.30700713, 0.96216923, 19.861904]","dataType":"DATA"}
{"time":1573073060742,"information":"world-aligned-accel","value":"[0.29670015, 0.9886859, 19.883423]","dataType":"DATA"}
{"time":1573073060802,"information":"world-aligned-accel","value":"[0.31168944, 0.9657618, 19.87297]","dataType":"DATA"}
{"time":1573073060868,"information":"world-aligned-accel","value":"[0.28237635, 0.9922832, 19.90905]","dataType":"DATA"}
{"time":1573073060926,"information":"world-aligned-accel","value":"[0.29108772, 0.9837343, 19.873238]","dataType":"DATA"}
{"time":1573073060992,"information":"world-aligned-accel","value":"[0.30088872, 0.97964, 19.867031]","dataType":"DATA"}
{"time":1573073061053,"information":"world-aligned-accel","value":"[0.30992183, 0.9748056, 19.884665]","dataType":"DATA"}
{"time":1573073061115,"information":"world-aligned-accel","value":"[0.30408782, 0.97306174, 19.879673]","dataType":"DATA"}
{"time":1573073061175,"information":"world-aligned-accel","value":"[0.30837405, 0.98625696, 19.893566]","dataType":"DATA"}
{"time":1573073061242,"information":"world-aligned-accel","value":"[0.28947026, 0.9884731, 19.885788]","dataType":"DATA"}
{"time":1573073061299,"information":"world-aligned-accel","value":"[0.3191004, 0.9864099, 19.891762]","dataType":"DATA"}
{"time":1573073061365,"information":"world-aligned-accel","value":"[0.31260425, 0.9766316, 19.878723]","dataType":"DATA"}
{"time":1573073061424,"information":"world-aligned-accel","value":"[0.30863237, 0.9777135, 19.881699]","dataType":"DATA"}
{"time":1573073061488,"information":"world-aligned-accel","value":"[0.30878347, 0.9805801, 19.88912]","dataType":"DATA"}
{"time":1573073061550,"information":"world-aligned-accel","value":"[0.30652165, 0.9852653, 19.88609]","dataType":"DATA"}
{"time":1573073061616,"information":"world-aligned-accel","value":"[0.30184704, 0.9880285, 19.88557]","dataType":"DATA"}
{"time":1573073061672,"information":"world-aligned-accel","value":"[0.30463645, 0.9865086, 19.892115]","dataType":"DATA"}
{"time":1573073061743,"information":"world-aligned-accel","value":"[0.2993728, 0.9790542, 19.890919]","dataType":"DATA"}
{"time":1573073061797,"information":"world-aligned-accel","value":"[0.31021833, 0.9811708, 19.881622]","dataType":"DATA"}
{"time":1573073061859,"information":"world-aligned-accel","value":"[0.29125887, 0.9836683, 19.89043]","dataType":"DATA"}
{"time":1573073061921,"information":"world-aligned-accel","value":"[0.3012395, 0.9886068, 19.890732]","dataType":"DATA"}
{"time":1573073061984,"information":"world-aligned-accel","value":"[0.30878213, 0.9620104, 19.872297]","dataType":"DATA"}
{"time":1573073062048,"information":"world-aligned-accel","value":"[0.30367935, 0.98727417, 19.898808]","dataType":"DATA"}
{"time":1573073062109,"information":"world-aligned-accel","value":"[0.29791886, 0.98845136, 19.86572]","dataType":"DATA"}
{"time":1573073062170,"information":"world-aligned-accel","value":"[0.2907264, 0.971315, 19.874897]","dataType":"DATA"}
{"time":1573073062235,"information":"world-aligned-accel","value":"[0.29305905, 0.97455966, 19.87489]","dataType":"DATA"}
{"time":1573073062299,"information":"world-aligned-accel","value":"[0.29220584, 0.984363, 19.90149]","dataType":"DATA"}
{"time":1573073062358,"information":"world-aligned-accel","value":"[0.31862307, 0.9540107, 19.864779]","dataType":"DATA"}
{"time":1573073062426,"information":"world-aligned-accel","value":"[0.29045016, 0.9712392, 19.88385]","dataType":"DATA"}
{"time":1573073062484,"information":"world-aligned-accel","value":"[0.29724365, 0.97673607, 19.886562]","dataType":"DATA"}
{"time":1573073062547,"information":"world-aligned-accel","value":"[0.30841124, 0.9865093, 19.880947]","dataType":"DATA"}
{"time":1573073062608,"information":"world-aligned-accel","value":"[0.2971226, 0.97974485, 19.892471]","dataType":"DATA"}
{"time":1573073062667,"information":"world-aligned-accel","value":"[0.30035755, 0.98333037, 19.869982]","dataType":"DATA"}
{"time":1573073062735,"information":"world-aligned-accel","value":"[0.29400474, 0.9765339, 19.866604]","dataType":"DATA"}
{"time":1573073062791,"information":"world-aligned-accel","value":"[0.29629463, 0.98072803, 19.883593]","dataType":"DATA"}
{"time":1573073062856,"information":"world-aligned-accel","value":"[0.30127007, 0.9846233, 19.880424]","dataType":"DATA"}
{"time":1573073062919,"information":"world-aligned-accel","value":"[0.30772465, 0.9792986, 19.885502]","dataType":"DATA"}
{"time":1573073062982,"information":"world-aligned-accel","value":"[0.30476797, 0.98684144, 19.888372]","dataType":"DATA"}
{"time":1573073063055,"information":"world-aligned-accel","value":"[0.30775493, 0.98631155, 19.873398]","dataType":"DATA"}
{"time":1573073063108,"information":"world-aligned-accel","value":"[0.292013, 0.98672175, 19.881441]","dataType":"DATA"}
{"time":1573073063169,"information":"world-aligned-accel","value":"[0.30687147, 0.9755813, 19.889935]","dataType":"DATA"}
{"time":1573073063228,"information":"world-aligned-accel","value":"[0.30810297, 0.9752512, 19.873611]","dataType":"DATA"}
{"time":1573073063292,"information":"world-aligned-accel","value":"[0.28683957, 0.98911065, 19.902996]","dataType":"DATA"}
{"time":1573073063353,"information":"world-aligned-accel","value":"[0.31433392, 0.9774426, 19.860802]","dataType":"DATA"}
{"time":1573073063413,"information":"world-aligned-accel","value":"[0.3066967, 0.9674446, 19.878958]","dataType":"DATA"}
{"time":1573073063478,"information":"world-aligned-accel","value":"[0.30188316, 0.99436283, 19.870468]","dataType":"DATA"}
{"time":1573073063540,"information":"world-aligned-accel","value":"[0.30970848, 0.98771304, 19.88974]","dataType":"DATA"}
{"time":1573073063606,"information":"world-aligned-accel","value":"[0.28615844, 0.9840552, 19.886631]","dataType":"DATA"}
{"time":1573073063668,"information":"world-aligned-accel","value":"[0.29875433, 0.98114574, 19.888622]","dataType":"DATA"}
{"time":1573073063726,"information":"world-aligned-accel","value":"[0.28772616, 0.98327017, 19.87767]","dataType":"DATA"}
{"time":1573073063788,"information":"world-aligned-accel","value":"[0.30088562, 0.9818455, 19.882633]","dataType":"DATA"}
